montague_pastedeploy/__init__.py
montague_pastedeploy/ini.py
montague_pastedeploy/upstream/__init__.py
montague_pastedeploy/upstream/config.py
montague_pastedeploy/upstream/converters.py
montague_pastedeploy/upstream/loadwsgi.py
montague_pastedeploy/upstream/util.py
montague_pastedeploy-0.2.0.dist-info/DESCRIPTION.rst
montague_pastedeploy-0.2.0.dist-info/entry_points.txt
montague_pastedeploy-0.2.0.dist-info/METADATA
montague_pastedeploy-0.2.0.dist-info/metadata.json
montague_pastedeploy-0.2.0.dist-info/RECORD
montague_pastedeploy-0.2.0.dist-info/top_level.txt
montague_pastedeploy-0.2.0.dist-info/WHEEL
